pysam_win-0.5.11.dist-info/DESCRIPTION.rst
pysam_win-0.5.11.dist-info/METADATA
pysam_win-0.5.11.dist-info/RECORD
pysam_win-0.5.11.dist-info/WHEEL
pysam_win-0.5.11.dist-info/metadata.json
pysam_win-0.5.11.dist-info/top_level.txt
pysam_windows/Pileup.py
pysam_windows/Pileup.pyc
pysam_windows/TabProxies.py
pysam_windows/TabProxies.pyc
pysam_windows/TabProxies.pyd
pysam_windows/__init__.py
pysam_windows/__init__.pyc
pysam_windows/csamtools.py
pysam_windows/csamtools.pyc
pysam_windows/csamtools.pyd
pysam_windows/ctabix.py
pysam_windows/ctabix.pyc
pysam_windows/ctabix.pyd
pysam_windows/cvcf.py
pysam_windows/cvcf.pyc
pysam_windows/cvcf.pyd
pysam_windows/namedtuple.py
pysam_windows/namedtuple.pyc
pysam_windows/version.py
pysam_windows/version.pyc
pysam_windows/EGG-INFO/PKG-INFO
pysam_windows/EGG-INFO/SOURCES.txt
pysam_windows/EGG-INFO/dependency_links.txt
pysam_windows/EGG-INFO/native_libs.txt
pysam_windows/EGG-INFO/not-zip-safe
pysam_windows/EGG-INFO/requires.txt
pysam_windows/EGG-INFO/top_level.txt
pysam_windows/pysam/Pileup.py
pysam_windows/pysam/Pileup.pyc
pysam_windows/pysam/__init__.py
pysam_windows/pysam/__init__.pyc
pysam_windows/pysam/namedtuple.py
pysam_windows/pysam/namedtuple.pyc
pysam_windows/pysam/version.py
pysam_windows/pysam/version.pyc
